qss_integrator-0.1.3.dist-info/METADATA
qss_integrator-0.1.3.dist-info/top_level.txt
qss_integrator-0.1.3.dist-info/WHEEL
qss_integrator-0.1.3.dist-info/RECORD
qss_integrator-0.1.3.dist-info/licenses/LICENSE
qss_integrator/utils.py
qss_integrator/__init__.py
qss_integrator/qss_py.cpython-39-x86_64-linux-gnu.so
qss_integrator/src/qss_python.cpp
qss_integrator/src/qss_integrator.h
qss_integrator/src/mathUtils.h
qss_integrator/src/qss_integrator.cpp
