Metadata-Version: 2.4
Name: qss-integrator
Version: 0.1.3
Summary: Quasi-Steady State method for stiff ODE systems with focus on combustion chemistry
Author-email: Eloghosa <eloghosaefficiency@gmail.com>
Maintainer-email: Eloghosa <eloghosaefficiency@gmail.com>
License: MIT
Project-URL: Homepage, https://github.com/elotech47/pyQSS
Project-URL: Documentation, https://github.com/elotech47/pyQSS/blob/main/README.md
Project-URL: Repository, https://github.com/elotech47/pyQSS.git
Project-URL: Issues, https://github.com/elotech47/pyQSS/issues
Keywords: ode,stiff,quasi-steady-state,combustion,chemical-kinetics,numerical-methods
Classifier: Development Status :: 3 - Alpha
Classifier: Intended Audience :: Science/Research
Classifier: Operating System :: OS Independent
Classifier: Programming Language :: Python :: 3
Classifier: Programming Language :: Python :: 3.8
Classifier: Programming Language :: Python :: 3.9
Classifier: Programming Language :: Python :: 3.10
Classifier: Programming Language :: Python :: 3.11
Classifier: Programming Language :: Python :: 3.12
Classifier: Programming Language :: C++
Classifier: Topic :: Scientific/Engineering :: Chemistry
Classifier: Topic :: Scientific/Engineering :: Mathematics
Classifier: Topic :: Scientific/Engineering :: Physics
Requires-Python: >=3.8
License-File: LICENSE
Requires-Dist: numpy>=1.16.0
Provides-Extra: dev
Requires-Dist: pytest>=6.0; extra == "dev"
Requires-Dist: pytest-cov; extra == "dev"
Requires-Dist: black; extra == "dev"
Requires-Dist: flake8; extra == "dev"
Requires-Dist: mypy; extra == "dev"
Provides-Extra: docs
Requires-Dist: sphinx; extra == "docs"
Requires-Dist: sphinx-rtd-theme; extra == "docs"
Requires-Dist: myst-parser; extra == "docs"
Provides-Extra: examples
Requires-Dist: cantera>=3.0; extra == "examples"
Requires-Dist: matplotlib>=3.0; extra == "examples"
Requires-Dist: scipy>=1.0; extra == "examples"
Dynamic: license-file
Dynamic: requires-python
